piemap/__init__.py
piemap/__main__.py
piemap/api.py
piemap/bitmap.py
piemap/cli.py
piemap/dsl.py
piemap/geometry.py
piemap/projections.py
piemap-2023.10.22.dist-info/LICENSE
piemap-2023.10.22.dist-info/METADATA
piemap-2023.10.22.dist-info/WHEEL
piemap-2023.10.22.dist-info/entry_points.txt
piemap-2023.10.22.dist-info/top_level.txt
piemap-2023.10.22.dist-info/RECORD
